clowns/__init__.py
clowns/starting.py
clowns/t/0.txt
clowns/t/1.txt
clowns/t/11.txt~
clowns/t/2.txt
clowns/t/3.txt
clowns/t/4.txt
clowns/t/5.txt
clowns/t/6.txt
clowns-2.0.dist-info/METADATA
clowns-2.0.dist-info/WHEEL
clowns-2.0.dist-info/licenses/LICENSE
clowns-2.0.dist-info/RECORD
