Metadata-Version: 2.1
Name: clowns
Version: 2.0
Summary: A Python library
Author-email: clown <clown@mail.ru>
License-File: LICENSE
Classifier: License :: OSI Approved :: MIT License
Classifier: Operating System :: OS Independent
Classifier: Programming Language :: Python :: 3
Requires-Python: >=3.9.0
